README.md
setup.py
Fuse_Explorer_API/__init__.py
Fuse_Explorer_API/account.py
Fuse_Explorer_API/block.py
Fuse_Explorer_API/client.py
Fuse_Explorer_API/contract.py
Fuse_Explorer_API/logs.py
Fuse_Explorer_API/stats.py
Fuse_Explorer_API/token.py
Fuse_Explorer_API/transaction.py
Fuse_Explorer_API.egg-info/PKG-INFO
Fuse_Explorer_API.egg-info/SOURCES.txt
Fuse_Explorer_API.egg-info/dependency_links.txt
Fuse_Explorer_API.egg-info/requires.txt
Fuse_Explorer_API.egg-info/top_level.txt